dj_all_auth/__init__.py
dj_all_auth/admin.py
dj_all_auth/apps.py
dj_all_auth/base_models.py
dj_all_auth/models.py
dj_all_auth/tests.py
dj_all_auth/urls.py
dj_all_auth/views.py
dj_all_auth/migrations/__init__.py
dj_all_auth/models/__init__.py
dj_all_auth/services/__init__.py
dj_all_auth/services/connections/__init__.py
dj_all_auth/services/connections/discord/Discord.py
dj_all_auth/services/connections/discord/__init__.py
dj_all_auth/services/connections/discord/models.py
dj_all_auth/services/connections/discord/urls.py
dj_all_auth/services/connections/discord/views.py
dj_all_auth/services/connections/google/Google.py
dj_all_auth/services/connections/google/__init__.py
dj_all_auth/services/connections/google/models.py
dj_all_auth/services/connections/google/urls.py
dj_all_auth/services/connections/google/views.py
dj_all_auth/services/connections/steam/Steam.py
dj_all_auth/services/connections/steam/__init__.py
dj_all_auth/services/connections/steam/models.py
dj_all_auth/services/connections/steam/urls.py
dj_all_auth/services/connections/steam/views.py
dj_all_auth/services/connections/twitch/Twitch.py
dj_all_auth/services/connections/twitch/__init__.py
dj_all_auth/services/connections/twitch/models.py
dj_all_auth/services/connections/twitch/urls.py
dj_all_auth/services/connections/twitch/views.py
dj_all_auth-0.1b19.dist-info/licenses/LICENSE
dj_all_auth-0.1b19.dist-info/METADATA
dj_all_auth-0.1b19.dist-info/WHEEL
dj_all_auth-0.1b19.dist-info/top_level.txt
dj_all_auth-0.1b19.dist-info/RECORD
