Metadata-Version: 2.4
Name: dj-all-auth
Version: 0.1b19
Summary: Django all auth includes all account, including django default, OAuth (Google, Discord, Twitch), openId (Steam).
Author-email: Deviser <deviserops+pypi@gmail.com>
License-Expression: BSD-3-Clause
Project-URL: Homepage, https://github.com/deviserops/dj-all-auth
Project-URL: Issues, https://github.com/deviserops/dj-all-auth/issues
Classifier: Programming Language :: Python :: 3
Classifier: Operating System :: OS Independent
Classifier: Environment :: Web Environment
Classifier: Framework :: Django
Classifier: Intended Audience :: Developers
Classifier: Operating System :: OS Independent
Classifier: Programming Language :: Python
Classifier: Programming Language :: Python :: 3
Classifier: Programming Language :: Python :: 3 :: Only
Classifier: Programming Language :: Python :: 3.10
Classifier: Programming Language :: Python :: 3.11
Classifier: Programming Language :: Python :: 3.12
Classifier: Topic :: Internet :: WWW/HTTP
Classifier: Topic :: Internet :: WWW/HTTP :: Dynamic Content
Requires-Python: >=3.10
License-File: LICENSE
Requires-Dist: Django>3
Dynamic: license-file
